data/__init__.py
data/i2p_sample/prompts/i2p.csv
data/prompts/__init__.py
data/prompts/church.csv
data/prompts/coco_10k.csv
data/prompts/coco_10k_sample.csv
data/prompts/coco_object_no_filter_retain.csv
data/prompts/coco_object_retain.csv
data/prompts/garbage_truck.csv
data/prompts/generic_dataset.csv
data/prompts/i2p.csv
data/prompts/illegal.csv
data/prompts/imagenet243_no_filter_retain.csv
data/prompts/imagenet243_retain.csv
data/prompts/nudity.csv
data/prompts/nudity_sample.csv
data/prompts/parachute.csv
data/prompts/prompts.csv
data/prompts/sample_prompt.csv
data/prompts/small_imagenet_prompts.csv
data/prompts/tench.csv
data/prompts/vangogh.csv
data/prompts/violence.csv
data/prompts/train/__init__.py
data/prompts/train/coco_object_no_filter_retain.csv
data/prompts/train/coco_object_retain.csv
data/prompts/train/coco_object_retain_sample.csv
data/prompts/train/imagenet243_no_filter_retain.csv
data/prompts/train/imagenet243_retain.csv
docs/.gitkeep
docs/README.md
docs/__init__.py
docs/project_architecture.md
docs/evaluation/README.md
docs/evaluation/adv_unlearn_evaluation.md
docs/evaluation/concept_ablation.md
docs/evaluation/contributing.md
docs/evaluation/erase_diff.md
docs/evaluation/esd.md
docs/evaluation/forget_me_not.md
docs/evaluation/saliency.md
docs/evaluation/scissorhands.md
docs/evaluation/semipermeable_membrane.md
docs/evaluation/uce.md
docs/evaluation/configs/adv_unlearn_evaluation.md
docs/evaluation/configs/concept_ablation.md
docs/evaluation/configs/erase_diff.md
docs/evaluation/configs/esd.md
docs/evaluation/configs/forget_me_not.md
docs/evaluation/configs/saliency.md
docs/evaluation/configs/scissorhands.md
docs/evaluation/configs/semipermeable_membrane.md
docs/evaluation/configs/uce.md
docs/mu_attack/Readme_MU_Attack.md
docs/mu_attack/mu_attack_evaluation.md
docs/mu_attack/attack/hard_prompt.md
docs/mu_attack/attack/no_attack.md
docs/mu_attack/attack/random.md
docs/mu_attack/attack/seed_search.md
docs/mu_attack/attack/soft_prompt.md
unlearn_diff-2.0.9.dist-info/METADATA
unlearn_diff-2.0.9.dist-info/WHEEL
unlearn_diff-2.0.9.dist-info/entry_points.txt
unlearn_diff-2.0.9.dist-info/top_level.txt
unlearn_diff-2.0.9.dist-info/RECORD
