Metadata-Version: 2.4
Name: unlearn_diff
Version: 2.0.9
Summary: Unlearning Algorithms
Home-page: https://github.com/RamailoTech/msu_unlearningalgorithm
Author: nebulaanish
Author-email: nebulaanish@gmail.com
Project-URL: Documentation, https://ramailotech.github.io/msu_unlearningalgorithm/
Project-URL: Source Code, https://github.com/RamailoTech/msu_unlearningalgorithm
Classifier: Programming Language :: Python :: 3
Classifier: License :: OSI Approved :: MIT License
Classifier: Operating System :: OS Independent
Requires-Python: >=3.7
Requires-Dist: pyyaml
Requires-Dist: setuptools
Requires-Dist: numpy<1.24,>=1.19.2
Requires-Dist: huggingface_hub==0.25.1
Requires-Dist: albumentations==0.4.3
Requires-Dist: datasets==2.8.0
Requires-Dist: bitsandbytes
Requires-Dist: tensorflow==2.12.0
Requires-Dist: diffusers==0.32.1
Requires-Dist: opencv-python==4.10.0.84
Requires-Dist: mediapipe==0.10.11
Requires-Dist: pudb==2019.2
Requires-Dist: imageio==2.9.0
Requires-Dist: imageio-ffmpeg==0.4.2
Requires-Dist: pytorch-lightning==1.8.5
Requires-Dist: omegaconf==2.1.1
Requires-Dist: test-tube>=0.7.5
Requires-Dist: streamlit>=0.73.1
Requires-Dist: einops==0.8.0
Requires-Dist: torch-fidelity==0.3.0
Requires-Dist: transformers==4.46.3
Requires-Dist: torchmetrics==0.11.4
Requires-Dist: kornia==0.6
Requires-Dist: tqdm==4.66.5
Requires-Dist: pandas==2.0.3
Requires-Dist: pyyaml==6.0.2
Requires-Dist: taming-transformers-rom1504
Requires-Dist: clip
Requires-Dist: openai
Requires-Dist: gradio
Requires-Dist: seaborn
Requires-Dist: loguru
Requires-Dist: ml_collections
Requires-Dist: webdataset
Requires-Dist: ftfy
Requires-Dist: yacs
Requires-Dist: controlnet_aux
Requires-Dist: fvcore
Requires-Dist: h5py
Requires-Dist: xtcocotools
Requires-Dist: natsort
Requires-Dist: timm==1.0.11
Requires-Dist: fairscale
Requires-Dist: open_clip_torch
Requires-Dist: wandb==0.18.7
Requires-Dist: quadprog
Requires-Dist: xformers
Requires-Dist: fire==0.7.0
Requires-Dist: terminaltables==3.1.10
Requires-Dist: pytest==8.3.4
Requires-Dist: gdown
Dynamic: author
Dynamic: author-email
Dynamic: classifier
Dynamic: description
Dynamic: description-content-type
Dynamic: home-page
Dynamic: project-url
Dynamic: requires-dist
Dynamic: requires-python
Dynamic: summary
